markethours/__init__.py
markethours/market_hours.py
tests/__init__.py
tests/test_market_hours.py
markethours-1.0.0.dist-info/LICENSE
markethours-1.0.0.dist-info/METADATA
markethours-1.0.0.dist-info/WHEEL
markethours-1.0.0.dist-info/top_level.txt
markethours-1.0.0.dist-info/RECORD
