Metadata-Version: 2.1
Name: markethours
Version: 1.0.0
Summary: A python library for referencing and localizing US stock trading hours
Home-page: https://github.com/mason-krause/markethours
Author: Mason Krause
Requires-Python: >=3.7
License-File: LICENSE
Requires-Dist: requests
Requires-Dist: pytz
Provides-Extra: dev
Requires-Dist: pytest ; extra == 'dev'
Requires-Dist: pytest-timeout ; extra == 'dev'
